django_changed_fields/__init__.py
django_changed_fields-0.3.1.dist-info/LICENSE
django_changed_fields-0.3.1.dist-info/METADATA
django_changed_fields-0.3.1.dist-info/WHEEL
django_changed_fields-0.3.1.dist-info/top_level.txt
django_changed_fields-0.3.1.dist-info/RECORD
