Metadata-Version: 2.1
Name: django-changed-fields
Version: 0.3.1
Summary: Testing installation of Package
Home-page: https://github.com/diegojsanches/DjangoChangedFields
Author: Diego Sanches
Author-email: diegojsanches@hotmail.com
License: MIT
Platform: UNKNOWN
License-File: LICENSE
